{
  "cards": [
    {
      "id": 1,
      "title": "Браслет черный",
      "img": "./img/brace.png",
      "desc": "lorem asgasg asgiouah snas d",
      "category": "bracelet",
      "price": "5000"
    },
    {
      "id": 2,
      "title": "Браслет серый",
      "img": "./img/brace.png",
      "desc": "lorem asgasg asgiouah snas d",
      "category": "bracelet",
      "price": "5000"
    },
    {
      "id": 3,
      "title": "Браслет синий",
      "img": "./img/brace.png",
      "desc": "lorem asgasg asgiouah snas d",
      "category": "bracelet",
      "price": "5000"
    }
  ]
}